[
  {
    "adminId": "373732650697097219",
    "orderNumber": "`OD000000147233327`",
    "hours": 3,
    "timestamp": "2025-10-15T02:23:32.009Z",
    "completedBy": "217998776311218176",
    "emailUid": "256322"
  },
  {
    "adminId": "217998776311218176",
    "orderNumber": "`OD000000147233327`",
    "hours": 2,
    "timestamp": "2025-10-15T02:23:33.666Z",
    "completedBy": "217998776311218176",
    "emailUid": "256322"
  },
  {
    "adminId": "599874563001679882",
    "orderNumber": "`OD000000147233327`",
    "hours": 1,
    "timestamp": "2025-10-15T02:57:46.213Z",
    "completedBy": "599874563001679882",
    "emailUid": "256322"
  }
]